setup.cfg
setup.py
data_processing/RandomData.py
data_processing/__init__.py
data_processing/tool.py
spider_tool/__init__.py
spider_tool/tool.py
znz_spider.egg-info/PKG-INFO
znz_spider.egg-info/SOURCES.txt
znz_spider.egg-info/dependency_links.txt
znz_spider.egg-info/requires.txt
znz_spider.egg-info/top_level.txt