Metadata-Version: 1.1
Name: znz-spider
Version: 0.1.0
Summary: 我还能说什么呢？
Home-page: https://github.com/zhangnaizhao/znz_spider.git
Author: zhangnaizhao
Author-email: zhang_naizhao@163.com
License: MIT
Platform: UNKNOWN
Classifier: Programming Language :: Python :: 3
Classifier: License :: OSI Approved :: MIT License
Classifier: Operating System :: OS Independent
